cis_checks_test_5/__init__.py
cis_checks_test_5/iam_control_1.py
cis_checks_test_5/logging_control_2.py
cis_checks_test_5/monitoring_control_3.py
cis_checks_test_5/networking_control_4.py
cis_checks_test_5/security_control_5.py
cis_checks_test_5/utils.py
cis_checks_test_5-0.0.7.dist-info/METADATA
cis_checks_test_5-0.0.7.dist-info/WHEEL
cis_checks_test_5-0.0.7.dist-info/top_level.txt
cis_checks_test_5-0.0.7.dist-info/RECORD
